raffle-1.1.1.dist-info/RECORD
raffle-1.1.1.dist-info/WHEEL
raffle-1.1.1.dist-info/METADATA
raffle-1.1.1.dist-info/licenses/LICENSE
raffle/__init__.py
raffle/_raffle.cpython-311-darwin.so
raffle/raffle.py
raffle/include/raffle.mod
raffle/etc/raffle__dist_calcs.mod
raffle/etc/raffle__viability.mod
raffle/etc/raffle__misc_linalg.mod
raffle/etc/raffle__geom_extd.mod
raffle/etc/raffle__distribs_container.mod
raffle/etc/raffle__distribs.mod
raffle/etc/raffle__misc.mod
raffle/etc/raffle__element_utils.mod
raffle/etc/raffle__misc_maths.mod
raffle/etc/raffle__cache.mod
raffle/etc/raffle__geom_rw.mod
raffle/etc/raffle__geom_utils.mod
raffle/etc/raffle__generator.mod
raffle/etc/raffle__evaluator.mod
raffle/etc/raffle__tools_infile.mod
raffle/etc/raffle__place_methods.mod
raffle/etc/raffle__io_utils.mod
raffle/etc/raffle__distribs_host.mod
raffle/etc/raffle__constants.mod
raffle/.dylibs/libgfortran.5.dylib
raffle/.dylibs/libquadmath.0.dylib
raffle/.dylibs/libgcc_s.1.1.dylib
raffle/.dylibs/libgomp.1.dylib
raffle/lib/libraffle.a
