Metadata-Version: 2.2
Name: raffle
Version: 1.1.1
Summary: A material interface structure prediction package
Author-Email: Ned Thaddeus Taylor <n.t.taylor@exeter.ac.uk>, Joe Pitfield <joepitfield@gmail.com>, Steven Paul Hepplestone <s.p.hepplestone@exeter.ac.uk>
License: GNU General Public License v3.0 or later
Classifier: Development Status :: 5 - Production/Stable
Classifier: Intended Audience :: Science/Research
Classifier: Programming Language :: Python :: 3.11
Classifier: Programming Language :: Python :: 3.12
Classifier: Programming Language :: Python :: 3.13
Classifier: Programming Language :: Fortran
Classifier: License :: OSI Approved :: GNU General Public License v3 (GPLv3)
Classifier: Operating System :: OS Independent
Project-URL: Homepage, https://github.com/ExeQuantCode/raffle
Project-URL: Documentation, https://raffle-fortran.readthedocs.io/
Project-URL: Repository, https://github.com/ExeQuantCode/raffle
Project-URL: Issues, https://github.com/ExeQuantCode/raffle/issues
Requires-Python: <3.14,>=3.11
Requires-Dist: ase>=3.23.0
Requires-Dist: numpy<=2.2,>=1.26.4
Requires-Dist: f90wrap<=0.2.16,>=0.2.14
Provides-Extra: tests
Requires-Dist: pytest; extra == "tests"
Requires-Dist: pytest-cov; extra == "tests"
Requires-Dist: parameterized; extra == "tests"
Requires-Dist: unittest; extra == "tests"
